sust/api/__init__.py
sust/api/climate_explorer.py
sust/api/test_climate_explorer.py
sust/api/util.py
sust/api/generated/__init__.py
sust/api/generated/climate_explorer/__init__.py
sust/api/generated/climate_explorer/api_client.py
sust/api/generated/climate_explorer/configuration.py
sust/api/generated/climate_explorer/exceptions.py
sust/api/generated/climate_explorer/model_utils.py
sust/api/generated/climate_explorer/rest.py
sust/api/generated/climate_explorer/api/__init__.py
sust/api/generated/climate_explorer/api/portfolios_api.py
sust/api/generated/climate_explorer/apis/__init__.py
sust/api/generated/climate_explorer/model/__init__.py
sust/api/generated/climate_explorer/model/asset_response.py
sust/api/generated/climate_explorer/model/errors_response.py
sust/api/generated/climate_explorer/model/message_response.py
sust/api/generated/climate_explorer/model/physical_risk_dataset_item_response.py
sust/api/generated/climate_explorer/model/physical_risk_dataset_summary_response.py
sust/api/generated/climate_explorer/model/physical_risk_exposure_extent.py
sust/api/generated/climate_explorer/model/physical_risk_exposure_item.py
sust/api/generated/climate_explorer/model/physical_risk_metadata_indicator_response.py
sust/api/generated/climate_explorer/model/physical_risk_metadata_response.py
sust/api/generated/climate_explorer/model/physical_risk_summary_item.py
sust/api/generated/climate_explorer/model/portfolio_create_request.py
sust/api/generated/climate_explorer/model/portfolio_response.py
sust/api/generated/climate_explorer/model/search_response.py
sust/api/generated/climate_explorer/model/search_response_feature.py
sust/api/generated/climate_explorer/model/search_response_physical_risk_exposure_property.py
sust/api/generated/climate_explorer/model/search_response_properties.py
sust/api/generated/climate_explorer/models/__init__.py
sust_api_client-0.0.91.dist-info/LICENSE
sust_api_client-0.0.91.dist-info/METADATA
sust_api_client-0.0.91.dist-info/WHEEL
sust_api_client-0.0.91.dist-info/top_level.txt
sust_api_client-0.0.91.dist-info/RECORD
